toasts/__init__.py
toasts/app.py
toasts/clients/__init__.py
toasts/clients/base.py
toasts/clients/github.py
toasts/data/config.yaml
toasts/data/icons/github.png
toasts/exceptions.py
toasts/main.py
toasts/util.py
toasts/wrappers.py
toasts-0.1.2.dist-info/entry_points.txt
toasts-0.1.2.dist-info/LICENSE.txt
toasts-0.1.2.dist-info/WHEEL
toasts-0.1.2.dist-info/METADATA
toasts-0.1.2.dist-info/RECORD
