Metadata-Version: 2.1
Name: toasts
Version: 0.1.2
Summary: Get desktop notifications from programming websites like GitHub, Stack Overflow and the likes :)
Home-page: https://github.com/gokulsoumya/toasts
License: MIT
Author: Gokul
Author-email: gokulps15@gmail.com
Requires-Python: >=3.4,<4.0
Classifier: License :: OSI Approved :: MIT License
Classifier: Programming Language :: Python :: 3
Classifier: Programming Language :: Python :: 3.4
Classifier: Programming Language :: Python :: 3.5
Classifier: Programming Language :: Python :: 3.6
Classifier: Programming Language :: Python :: 3.7
Requires-Dist: confuse (>=0.5.0,<0.6.0)
Requires-Dist: dbus-python (>=1.2,<2.0); sys_platform == "linux"
Requires-Dist: plyer (>=1.3.0,<2.0.0)
Requires-Dist: requests (>=2.19,<3.0)
Project-URL: Repository, https://github.com/gokulsoumya/toasts
